{
  "issuer_name": "CT Real Estate Investment Trust",
  "reporting_date": "2023-03-31",
  "reporting_period": "Q1 2023",
  "currency": "CAD",
  "balance_sheet": {
    "common_units_outstanding": 198404,
    "diluted_units_outstanding": 233643
  },
  "leverage_metrics": {
    "total_debt": 2786501,
    "net_debt": 2781267,
    "gross_assets": 6863797,
    "debt_to_assets_percent": 40.6,
    "net_debt_ratio": 40.52
  },
  "reit_metrics": {
    "ffo": 75328,
    "affo": 69231,
    "ffo_per_unit": 0.321,
    "affo_per_unit": 0.295,
    "distributions_per_unit": 0.217,
    "ffo_payout_ratio": 67.6,
    "affo_payout_ratio": 73.6,
    "source": "issuer_reported",
    "ffo_per_unit_diluted": 0.321,
    "affo_per_unit_diluted": 0.295,
    "ffo_calculated": 74486.0,
    "affo_calculated": 68635.0,
    "ffo_calculation_detail": {
      "ffo_calculated": 74486.0,
      "net_income_ifrs": 70511,
      "total_adjustments": 3975.0,
      "adjustments_detail": {
        "adjustment_A_unrealized_fv_changes": 4180,
        "adjustment_B_depreciation_real_estate": 0,
        "adjustment_C_amortization_tenant_allowances": 0,
        "adjustment_D_amortization_intangibles": 0,
        "adjustment_E_gains_losses_property_sales": 0,
        "adjustment_F_tax_on_disposals": 0,
        "adjustment_G_deferred_taxes": 444,
        "adjustment_H_impairment_losses_reversals": 0,
        "adjustment_I_revaluation_gains_losses": 0,
        "adjustment_J_transaction_costs_business_comb": 0,
        "adjustment_K_foreign_exchange_gains_losses": 0,
        "adjustment_L_sale_foreign_operations": 0,
        "adjustment_M_fv_changes_hedges": 0,
        "adjustment_N_goodwill_impairment": 0,
        "adjustment_O_puttable_instruments_effects": 0,
        "adjustment_P_discontinued_operations": 0,
        "adjustment_Q_equity_accounted_adjustments": 0,
        "adjustment_R_incremental_leasing_costs": 0,
        "adjustment_S_property_taxes_ifric21": 0,
        "adjustment_T_rou_asset_revenue_expense": -351,
        "adjustment_U_non_controlling_interests_ffo": 298
      },
      "missing_components": [],
      "available_adjustments": 21,
      "total_adjustments_count": 21,
      "data_quality": "strong",
      "ffo_per_unit": 0.3754,
      "ffo_per_unit_diluted": 0.3188
    },
    "affo_calculation_detail": {
      "affo_calculated": 68635.0,
      "ffo_starting_point": 74486.0,
      "total_adjustments": -5851.0,
      "adjustments_detail": {
        "adjustment_V_capex_sustaining": -6327,
        "adjustment_W_leasing_costs": -192,
        "adjustment_X_tenant_improvements": 0,
        "adjustment_Y_straight_line_rent": 422,
        "adjustment_Z_non_controlling_interests_affo": 246
      },
      "missing_components": [],
      "available_adjustments": 5,
      "total_adjustments_count": 5,
      "calculation_method": "reserve",
      "reserve_methodology": "Capital expenditure reserve based on average expenditures from building condition reports prepared by independent consultants",
      "data_quality": "strong",
      "affo_per_unit": 0.3459,
      "affo_per_unit_diluted": 0.2938
    },
    "validation": {
      "ffo_variance_amount": -842.0,
      "ffo_variance_percent": -1.12,
      "ffo_within_threshold": true,
      "affo_variance_amount": -596.0,
      "affo_variance_percent": -0.86,
      "affo_within_threshold": true,
      "validation_notes": [
        "FFO calculation validated: -1.1% variance (within 5% threshold).",
        "AFFO calculation validated: -0.9% variance (within 5% threshold)."
      ],
      "validation_summary": "FFO calculation validated: -1.1% variance (within 5% threshold). AFFO calculation validated: -0.9% variance (within 5% threshold)."
    },
    "acfo_calculated": 100107.0,
    "acfo_calculation_detail": {
      "acfo_calculated": 100107.0,
      "cash_flow_from_operations": 122368,
      "total_adjustments": -22261.0,
      "adjustments_detail": {
        "adjustment_1_change_in_working_capital": -15988,
        "adjustment_2_interest_financing": 0,
        "adjustment_3a_jv_distributions": 0,
        "adjustment_3b_jv_acfo": 0,
        "adjustment_3c_jv_notional_interest": 0,
        "adjustment_4_capex_sustaining_acfo": -6327,
        "adjustment_4_dev_capex_development_acfo": 0,
        "adjustment_5_leasing_costs_external": -192,
        "adjustment_6_tenant_improvements_acfo": 0,
        "adjustment_7_realized_investment_gains_losses": 0,
        "adjustment_8_taxes_non_operating": 0,
        "adjustment_9_transaction_costs_acquisitions": 0,
        "adjustment_10_transaction_costs_disposals": 0,
        "adjustment_11_deferred_financing_fees": 0,
        "adjustment_12_debt_termination_costs": 0,
        "adjustment_13a_off_market_debt_favorable": 0,
        "adjustment_13b_off_market_debt_unfavorable": 0,
        "adjustment_14a_interest_income_timing": 0,
        "adjustment_14b_interest_expense_timing": 0,
        "adjustment_15_puttable_instruments_distributions": 0,
        "adjustment_16a_rou_sublease_principal_received": 0,
        "adjustment_16b_rou_sublease_interest_received": 0,
        "adjustment_16c_rou_lease_principal_paid": 0,
        "adjustment_16d_rou_depreciation_amortization": 0,
        "adjustment_17a_non_controlling_interests_acfo": 246,
        "adjustment_17b_nci_puttable_units": 0
      },
      "missing_components": [],
      "available_adjustments": 26,
      "total_adjustments_count": 17,
      "calculation_method": "reserve",
      "jv_treatment_method": "distributions",
      "reserve_methodology": "Capital expenditure reserve and leasing costs based on average historical expenditures",
      "consistency_checks": {
        "capex_match": true,
        "capex_variance": 0,
        "tenant_improvements_match": true,
        "tenant_improvements_variance": 0
      },
      "data_quality": "strong",
      "acfo_per_unit": 0.5046,
      "acfo_per_unit_diluted": 0.4285
    },
    "acfo_validation": {
      "acfo_variance_amount": null,
      "acfo_variance_percent": null,
      "acfo_within_threshold": null,
      "validation_notes": [],
      "validation_summary": ""
    },
    "acfo": 0
  },
  "coverage_ratios": {
    "noi_interest_coverage": 3.55,
    "annualized_interest_expense": 126952,
    "period_interest_expense": 31738,
    "annualization_factor": 4,
    "detected_period": "quarterly_q1"
  },
  "portfolio_metrics": {
    "total_properties": 364,
    "gla_sf": 31009000,
    "occupancy_rate": 0.997,
    "occupancy_including_commitments": 0.997,
    "same_property_noi_growth": 0
  },
  "afcf_metrics": {
    "afcf": -21789.0,
    "acfo_starting_point": 0,
    "net_cfi": -21789.0,
    "cfi_breakdown": {
      "development_capex": {
        "description": "Development CAPEX (growth projects)",
        "amount": -21614
      },
      "property_acquisitions": {
        "description": "Property acquisitions",
        "amount": 0
      },
      "property_dispositions": {
        "description": "Property dispositions (proceeds)",
        "amount": 0
      },
      "jv_capital_contributions": {
        "description": "JV capital contributions",
        "amount": 0
      },
      "jv_return_of_capital": {
        "description": "JV return of capital",
        "amount": 0
      },
      "business_combinations": {
        "description": "Business combinations",
        "amount": 0
      },
      "other_investing_outflows": {
        "description": "Other investing outflows",
        "amount": -175
      },
      "other_investing_inflows": {
        "description": "Other investing inflows",
        "amount": 0
      }
    },
    "missing_components": [],
    "available_components": 8,
    "total_components": 8,
    "data_quality": "strong",
    "has_cfi_data": true,
    "reconciliation_check": {
      "calculated_net_cfi": -21789.0,
      "reported_total_cfi": -21789,
      "variance": 0.0,
      "matches": true
    },
    "afcf_per_unit": -0.1098,
    "afcf_per_unit_diluted": -0.0933
  },
  "afcf_coverage": {
    "afcf_debt_service_coverage": -0.64,
    "afcf_distribution_coverage": -0.45,
    "afcf_payout_ratio": -223.2,
    "afcf_self_funding_ratio": -0.26,
    "total_debt_service": 33842,
    "total_distributions": 48635,
    "net_financing_needs": 68477,
    "data_quality": "strong",
    "afcf_self_funding_capacity": -104266.0
  },
  "afcf_reconciliation": {
    "afcf_calculation_valid": true,
    "acfo_cfi_reconciles": true,
    "cash_flow_statement_reconciles": true,
    "development_capex_consistent": false,
    "validation_notes": [
      "\u2713 AFCF calculation correct: ACFO + Net CFI = AFCF",
      "\u26a0 Development CAPEX mismatch: ACFO (0) vs CFI (-21,614)",
      "\u2139 Cash flow components: CFO (122,368) + CFI (-21,789) + CFF (-36,838) = 63,741"
    ],
    "reconciliation_summary": "\u2713 AFCF calculation correct: ACFO + Net CFI = AFCF | \u26a0 Development CAPEX mismatch: ACFO (0) vs CFI (-21,614) | \u2139 Cash flow components: CFO (122,368) + CFI (-21,789) + CFF (-36,838) = 63,741"
  },
  "burn_rate_analysis": {
    "applicable": true,
    "monthly_burn_rate": -34755.33,
    "period_burn_rate": -104266.0,
    "period_months": 3,
    "afcf": -21789.0,
    "mandatory_obligations": 82477,
    "self_funding_ratio": -0.26,
    "reason": null,
    "data_quality": "strong"
  },
  "liquidity_position": {
    "cash_and_equivalents": 5234,
    "marketable_securities": 0,
    "restricted_cash": 0,
    "undrawn_credit_facilities": 568000,
    "credit_facility_limit": 900000,
    "available_cash": 5234,
    "total_available_liquidity": 573234,
    "data_source": "Balance sheet and Note 9 - Credit Facilities. Bank Credit Facility: $800M limit with $332M drawn = $468M available. CTC Credit Facility: $100M limit with $0 drawn = $100M available. Total undrawn: $568M."
  },
  "cash_runway": {
    "runway_months": 0.2,
    "runway_years": 0.0,
    "extended_runway_months": 16.5,
    "extended_runway_years": 1.4,
    "depletion_date": "2023-04-04",
    "available_cash": 5234,
    "total_available_liquidity": 573234,
    "data_quality": "strong",
    "error": null,
    "extended_depletion_date": "2024-08-07"
  },
  "liquidity_risk": {
    "risk_level": "CRITICAL",
    "risk_score": 4,
    "warning_flags": [
      "Cash depletion imminent",
      "Emergency financing needed",
      "Going concern risk"
    ],
    "assessment": "\ud83d\udea8 Immediate financing required - runway < 6 months",
    "recommendations": [
      "Suspend or reduce distributions immediately",
      "Accelerate non-core asset sales",
      "Pursue emergency financing (bridge loan, equity raise)",
      "Defer all non-critical capital expenditures",
      "Engage restructuring advisors"
    ],
    "data_quality": "strong"
  },
  "sustainable_burn": {
    "target_runway_months": 24,
    "sustainable_monthly_burn": 218.08,
    "actual_monthly_burn": -34755.33,
    "excess_burn_per_month": 34537.25,
    "excess_burn_annualized": 414446.96,
    "status": "Above sustainable - Overspending by $34,537/month",
    "available_cash": 5234,
    "data_quality": "strong"
  },
  "dilution_analysis": {
    "has_dilution_detail": true,
    "dilution_percentage": 17.76,
    "dilution_materiality": "high",
    "material_instruments": [
      {
        "instrument": "other",
        "units": 34952,
        "dilution_pct": 17.62
      }
    ],
    "convertible_debt_risk": "none",
    "governance_score": "enhanced",
    "credit_assessment": "\ud83d\udea8 HIGH dilution - material equity overhang, review impact on debt capacity and unit holder value dilution",
    "detail": {
      "basic_units": 198404,
      "dilutive_instruments": {
        "restricted_units": 287,
        "deferred_units": 0,
        "stock_options": 0,
        "convertible_debentures": 0,
        "warrants": 0,
        "other": 34952
      },
      "diluted_units_calculated": 233643,
      "diluted_units_reported": 233643,
      "dilution_percentage": 17.76,
      "reconciliation_note": "Dilution includes restricted units under unit-based compensation plans (287k) and other dilutive securities (34,952k). Excludes Class C LP Units conversion as per REIT methodology.",
      "disclosure_source": "Q1 2023 Interim Financial Statements Note 10"
    }
  }
}